{"nodes": [{"id": "sfx_credits_sfx_library", "label": "SFX library: Pixabay-licensed sound effects bundled with website-to-hyperframes skill", "file_type": "document", "source_file": ".agents/skills/website-to-hyperframes/assets/sfx/CREDITS.md", "source_location": null, "source_url": null, "captured_at": null, "author": null, "contributor": null}], "edges": [{"source": "sfx_credits_sfx_library", "target": "website_to_hyperframes_skill_w2hf_workflow", "relation": "references", "confidence": "INFERRED", "confidence_score": 0.85, "source_file": ".agents/skills/website-to-hyperframes/assets/sfx/CREDITS.md", "source_location": null, "weight": 0.85}], "hyperedges": []}