{"nodes": [{"id": "hyperframes_visualstyles_8_styles", "label": "Visual Style Library (8 named design traditions)", "file_type": "document", "source_file": ".agents/skills/hyperframes/visual-styles.md", "source_location": null, "source_url": null, "captured_at": null, "author": null, "contributor": null}, {"id": "hyperframes_visualstyles_swiss_pulse", "label": "Swiss Pulse Style (clinical/precise, SaaS)", "file_type": "concept", "source_file": ".agents/skills/hyperframes/visual-styles.md", "source_location": "line 24-68", "source_url": null, "captured_at": null, "author": null, "contributor": null}, {"id": "hyperframes_visualstyles_shadow_cut", "label": "Shadow Cut Style (dark/cinematic, security/drama)", "file_type": "concept", "source_file": ".agents/skills/hyperframes/visual-styles.md", "source_location": "line 372-416", "source_url": null, "captured_at": null, "author": null, "contributor": null}], "edges": [{"source": "hyperframes_visualstyles_8_styles", "target": "hyperframes_visualstyles_swiss_pulse", "relation": "references", "confidence": "EXTRACTED", "confidence_score": 1.0, "source_file": ".agents/skills/hyperframes/visual-styles.md", "source_location": "line 24", "weight": 1.0}, {"source": "hyperframes_visualstyles_8_styles", "target": "hyperframes_visualstyles_shadow_cut", "relation": "references", "confidence": "EXTRACTED", "confidence_score": 1.0, "source_file": ".agents/skills/hyperframes/visual-styles.md", "source_location": "line 372", "weight": 1.0}], "hyperedges": []}